odoo/addons/l10n_it_vat_statement_split_payment/README.rst
odoo/addons/l10n_it_vat_statement_split_payment/__init__.py
odoo/addons/l10n_it_vat_statement_split_payment/__manifest__.py
odoo/addons/l10n_it_vat_statement_split_payment/i18n/it.po
odoo/addons/l10n_it_vat_statement_split_payment/i18n/l10n_it_vat_statement_split_payment.pot
odoo/addons/l10n_it_vat_statement_split_payment/models/__init__.py
odoo/addons/l10n_it_vat_statement_split_payment/models/account.py
odoo/addons/l10n_it_vat_statement_split_payment/models/account_config.py
odoo/addons/l10n_it_vat_statement_split_payment/models/res_company.py
odoo/addons/l10n_it_vat_statement_split_payment/models/statement.py
odoo/addons/l10n_it_vat_statement_split_payment/readme/CONFIGURE.md
odoo/addons/l10n_it_vat_statement_split_payment/readme/CONTRIBUTORS.md
odoo/addons/l10n_it_vat_statement_split_payment/readme/CREDITS.md
odoo/addons/l10n_it_vat_statement_split_payment/readme/DESCRIPTION.md
odoo/addons/l10n_it_vat_statement_split_payment/readme/USAGE.md
odoo/addons/l10n_it_vat_statement_split_payment/static/description/icon.png
odoo/addons/l10n_it_vat_statement_split_payment/static/description/index.html
odoo/addons/l10n_it_vat_statement_split_payment/tests/__init__.py
odoo/addons/l10n_it_vat_statement_split_payment/tests/test_vat_statement_split.py
odoo/addons/l10n_it_vat_statement_split_payment/views/account_config_view.xml
odoo_addon_l10n_it_vat_statement_split_payment-16.0.1.0.0.11.dist-info/METADATA
odoo_addon_l10n_it_vat_statement_split_payment-16.0.1.0.0.11.dist-info/WHEEL
odoo_addon_l10n_it_vat_statement_split_payment-16.0.1.0.0.11.dist-info/top_level.txt
odoo_addon_l10n_it_vat_statement_split_payment-16.0.1.0.0.11.dist-info/RECORD
